Metadata-Version: 1.0
Name: gaussbino
Version: 0.1
Summary: Gaussian distributions
Home-page: UNKNOWN
Author: Piyush Kumar
Author-email: UNKNOWN
License: UNKNOWN
Platform: UNKNOWN
